baotool/__init__.py
baotool/decorator/__init__.py
baotool-1.0.1.dist-info/METADATA
baotool-1.0.1.dist-info/WHEEL
baotool-1.0.1.dist-info/top_level.txt
baotool-1.0.1.dist-info/RECORD
